CHANGELOG.md
yotse/__init__.py
yotse/execution.py
yotse/optimization/__init__.py
yotse/optimization/blackbox_algorithms.py
yotse/optimization/fitting.py
yotse/optimization/generic_optimization.py
yotse/optimization/modded_pygad_ga.py
yotse/optimization/optimizer.py
yotse/optimization/whitebox_algorithms.py
yotse/post.py
yotse/pre.py
yotse/utils/__init__.py
yotse/utils/blueprint_tools.py
yotse/utils/prediction.py
yotse/utils/utils.py
yotse-1.0.0.dist-info/LICENSE
yotse-1.0.0.dist-info/METADATA
yotse-1.0.0.dist-info/WHEEL
yotse-1.0.0.dist-info/entry_points.txt
yotse-1.0.0.dist-info/RECORD
