Metadata-Version: 2.1
Name: yotse
Version: 1.0.0
Summary: Your Optimization Tool for Scientific Experiments
Home-page: https://github.com/SURFQuantum/yotse
License: Apache-2.0
Keywords: science,optimization,genetic,algorithm,gradient,experiment
Author: dmark04
Author-email: dmark04@web.de
Requires-Python: >=3.9,<3.13
Classifier: Development Status :: 4 - Beta
Classifier: License :: OSI Approved :: Apache Software License
Classifier: Operating System :: OS Independent
Classifier: Programming Language :: Python :: 3
Classifier: Programming Language :: Python :: 3.9
Classifier: Programming Language :: Python :: 3.10
Classifier: Programming Language :: Python :: 3.11
Classifier: Programming Language :: Python :: 3.12
Classifier: Topic :: Scientific/Engineering
Requires-Dist: bayesian-optimization (>=1.4.3,<2.0.0)
Requires-Dist: pandas (>=2.0.0,<3.0.0)
Requires-Dist: pygad (>=3.0.0,<3.1.0)
Requires-Dist: qcg-pilotjob (>=0.14.1,<0.15.0)
Requires-Dist: ruamel-yaml (>=0.17.40,<0.18.0)
Requires-Dist: scipy (>=1.11.4,<2.0.0)
Project-URL: Documentation, https://surfquantum.github.io/yotse/
Project-URL: Repository, https://github.com/SURFQuantum/yotse
